TwentyTwentiesHumorBot/Distorter.py
TwentyTwentiesHumorBot/FileHandler.py
TwentyTwentiesHumorBot/ImageCaptioner.py
TwentyTwentiesHumorBot/ImageTweeter.py
TwentyTwentiesHumorBot/NameStupifier.py
TwentyTwentiesHumorBot/ObjectDetector.py
TwentyTwentiesHumorBot/TwentyTwentiesHumorBot.py
TwentyTwentiesHumorBot/__init__.py
TwentyTwentiesHumorBot/__main__.py
TwentyTwentiesHumorBot-1.0.0.dist-info/LICENSE
TwentyTwentiesHumorBot-1.0.0.dist-info/METADATA
TwentyTwentiesHumorBot-1.0.0.dist-info/WHEEL
TwentyTwentiesHumorBot-1.0.0.dist-info/entry_points.txt
TwentyTwentiesHumorBot-1.0.0.dist-info/top_level.txt
TwentyTwentiesHumorBot-1.0.0.dist-info/RECORD
