Metadata-Version: 2.1
Name: TwentyTwentiesHumorBot
Version: 1.0.0
Summary: TwentyTwentiesHumorBot is a bot which takes images, makes them stupid with the power of AI, and then posts them to twitter.
Home-page: http://www.pixelatedawesome.com/projects/2020sHumorBot/
Author: Daniel Westbrook
Author-email: dan@pixelatedawesome.com
License: UNKNOWN
Keywords: bot,AI,bulge,distorted,twitter,image,distortion,meme,memes,funny,humor,fun
Platform: UNKNOWN
Classifier: Development Status :: 5 - Production/Stable
Classifier: License :: OSI Approved :: MIT License
Classifier: Intended Audience :: Information Technology
Classifier: Intended Audience :: System Administrators
Classifier: Intended Audience :: Developers
Classifier: Operating System :: OS Independent
Classifier: Programming Language :: Python :: 3 :: Only
Classifier: Programming Language :: Python :: 3
Classifier: Topic :: Scientific/Engineering :: Artificial Intelligence
Classifier: Topic :: Scientific/Engineering :: Image Recognition
License-File: LICENSE
Requires-Dist: EasyTweeter (>='0.10.0')
Requires-Dist: imageai
Requires-Dist: pillow
Requires-Dist: numpy
Requires-Dist: opencv-python
Requires-Dist: tensorflow
